aligned_widgets/__init__.py
aligned_widgets/base.py
aligned_widgets/control_widget.py
aligned_widgets/file_server.py
aligned_widgets/helpers.py
aligned_widgets/timeseries_widget.py
aligned_widgets/video_widget.py
aligned_widgets/static/add.svg
aligned_widgets/static/control_widget.css
aligned_widgets/static/control_widget.js
aligned_widgets/static/delete.svg
aligned_widgets/static/pause.svg
aligned_widgets/static/play.svg
aligned_widgets/static/timeseries_widget.css
aligned_widgets/static/timeseries_widget.js
aligned_widgets/static/video_widget.css
aligned_widgets/static/video_widget.js
aligned_widgets/static/zoom_in.svg
aligned_widgets/static/zoom_out.svg
aligned_widgets-0.0.4.dist-info/METADATA
aligned_widgets-0.0.4.dist-info/WHEEL
aligned_widgets-0.0.4.dist-info/licenses/LICENSE
aligned_widgets-0.0.4.dist-info/RECORD
