Metadata-Version: 2.4
Name: aligned_widgets
Version: 0.0.4
Summary: A set of Jupyter Notebook widgets which let you visualize synchronized multimodal data.
Author-email: Usama Ahmed Siddiquie <220usamaahmed@gmail.com>
License-Expression: MIT
License-File: LICENSE
Requires-Dist: anywidget>=0.9.18
Requires-Dist: flask>=3.1.1
Requires-Dist: numpy>=2.2.6
Requires-Dist: werkzeug>=3.1.3
Provides-Extra: dev
Requires-Dist: build; extra == 'dev'
Requires-Dist: jupyterlab; extra == 'dev'
Requires-Dist: twine; extra == 'dev'
Requires-Dist: watchfiles; extra == 'dev'
